wvmos/__init__.py
wvmos/wv_mos.py
wvmos-1.0.dist-info/METADATA
wvmos-1.0.dist-info/WHEEL
wvmos-1.0.dist-info/top_level.txt
wvmos-1.0.dist-info/RECORD
