Metadata-Version: 2.1
Name: wvmos
Version: 1.0
Summary: This package is written for MOS score prediction based on fine-tuned wav2vec2.0 model
Home-page: https://github.com/AndreevP/wvmos
Author: Pavel Andreev
Author-email: andreev.pk@phystech.edu
Requires-Python: >=3.9.0
Requires-Dist: numpy
Requires-Dist: scipy
Requires-Dist: tqdm
Requires-Dist: librosa
Requires-Dist: torch >=1.7.0
Requires-Dist: transformers >=4.12.5
Requires-Dist: pytorch-lightning >=1.5.5
